{"cameraMode":{"drawMode":0,"name":"Shaded","section":"Shading Mode"},"sceneLighting":false,"audioPlay":false,"sceneViewState":{"showFog":true,"showMaterialUpdate":false,"showSkybox":false,"showFlares":true,"showImageEffects":true,"showParticleSystems":true},"in2DMode":false,"pivot":{"x":36.563629150390628,"y":0.222181499004364,"z":-31.474369049072267},"rotation":{"x":0.4195641279220581,"y":0.09096985310316086,"z":-0.042306896299123767,"w":0.9021658301353455},"size":1.4860177040100098,"orthographic":false}